README.rst
setup.py
patella/__init__.py
patella/__main__.py
patella/click_commands.py
patella/htmlparser.py
patella/patellaserver.py
patella/tablereader.py
patella.egg-info/PKG-INFO
patella.egg-info/SOURCES.txt
patella.egg-info/dependency_links.txt
patella.egg-info/entry_points.txt
patella.egg-info/requires.txt
patella.egg-info/top_level.txt