Metadata-Version: 1.1
Name: patella
Version: 0.1.12
Summary: A webservice for scraping files and plotting data against presidential party variation
Home-page: https://github.com/salbrandi/patella
Author: Salvador Brandi
Author-email: salbrandi@gmail.com
License: UNKNOWN
Download-URL: https://github.com/salbrandi/patella/archive/0.1.tar.gz
Keywords: plotting data party presidential office term year bokeh
Platform: UNKNOWN
Classifier: Development Status :: 3 - Alpha
Classifier: Programming Language :: Python :: 3 :: Only
